dat1/__init__.py
dat1/handler/common.py
dat1/handler/diffusion_handler.py
dat1_runtime-0.1.5.dist-info/METADATA
dat1_runtime-0.1.5.dist-info/WHEEL
dat1_runtime-0.1.5.dist-info/RECORD
